LICENSE
README.rst
setup.py
longmao_point_cloud_converter.egg-info/PKG-INFO
longmao_point_cloud_converter.egg-info/SOURCES.txt
longmao_point_cloud_converter.egg-info/dependency_links.txt
longmao_point_cloud_converter.egg-info/requires.txt
longmao_point_cloud_converter.egg-info/top_level.txt
npccp/__init__.py
npccp/npccp.py
npccp/pcd/PcdReader.py
npccp/pcd/PcdWriter.py
npccp/pcd/__init__.py
npccp/pcd/utils/PcdUtils.py
npccp/pcd/utils/__init__.py
npccp/potree/HBatch.py
npccp/potree/HChunk.py
npccp/potree/HNode.py
npccp/potree/Node.py
npccp/potree/Point.py
npccp/potree/PotreeWriter.py
npccp/potree/__init__.py
npccp/potree/sampler/PotreeIndexerSampler.py
npccp/potree/sampler/PotreeIndexerSamplerStep.py
npccp/potree/sampler/__init__.py