Metadata-Version: 2.1
Name: longmao-point-cloud-converter
Version: 0.0.1
Summary: The official LongMao SDK for Python.
Home-page: https://github.com/nayuan/point-cloud-converter-python
Author: nayuan
Author-email: haojunsheng@longmaosoft.com
License: Apache
Keywords: point-cloud,potree,pcd
Platform: any
Classifier: Intended Audience :: Developers
Classifier: License :: OSI Approved :: Apache Software License
Classifier: Programming Language :: Python
Classifier: Programming Language :: Python :: 2.6
Classifier: Programming Language :: Python :: 2.7
Classifier: Programming Language :: Python :: 3
Classifier: Programming Language :: Python :: 3.3
Classifier: Topic :: Software Development
License-File: LICENSE
